sphinx_scylladb_markdown/__init__.py
sphinx_scylladb_markdown-0.1.4.dist-info/licenses/LICENSE
sphinx_scylladb_markdown-0.1.4.dist-info/METADATA
sphinx_scylladb_markdown-0.1.4.dist-info/WHEEL
sphinx_scylladb_markdown-0.1.4.dist-info/top_level.txt
sphinx_scylladb_markdown-0.1.4.dist-info/RECORD
