Metadata-Version: 2.4
Name: sphinx-scylladb-markdown
Version: 0.1.4
Summary: Sphinx extension for ScyllaDB documentation with enhanced Markdown support through MystParser and recommonmark.
Home-page: https://github.com/scylladb/sphinx-scylladb-theme
Author: David Garcia
Author-email: hi@davidgarcia.dev
License-File: LICENSE
Requires-Dist: sphinx>=2.1
Requires-Dist: recommonmark==0.7.1
Requires-Dist: sphinx-markdown-tables==0.0.17
Requires-Dist: myst-parser>=2.0.0
Dynamic: author
Dynamic: author-email
Dynamic: description
Dynamic: description-content-type
Dynamic: home-page
Dynamic: license-file
Dynamic: requires-dist
Dynamic: summary
